__init__.py
nsqip_tools/__init__.py
nsqip_tools/builder.py
nsqip_tools/config.py
nsqip_tools/constants.py
nsqip_tools/data_dictionary.py
nsqip_tools/query.py
nsqip_tools/_internal/__init__.py
nsqip_tools/_internal/ingest.py
nsqip_tools/_internal/inspect.py
nsqip_tools/_internal/memory_utils.py
nsqip_tools/_internal/transform.py
nsqip_tools-0.2.3.dist-info/licenses/LICENSE
nsqip_tools-0.2.3.dist-info/METADATA
nsqip_tools-0.2.3.dist-info/WHEEL
nsqip_tools-0.2.3.dist-info/top_level.txt
nsqip_tools-0.2.3.dist-info/RECORD
