Metadata-Version: 2.4
Name: nsqip-tools
Version: 0.2.3
Summary: Tools for working with NSQIP surgical quality data
Author: Jason Brant
License: MIT
Project-URL: Homepage, https://github.com/brant01/nsqip_tools
Project-URL: Bug Tracker, https://github.com/brant01/nsqip_tools/issues
Project-URL: Source Code, https://github.com/brant01/nsqip_tools
Classifier: Development Status :: 4 - Beta
Classifier: Intended Audience :: Healthcare Industry
Classifier: Intended Audience :: Science/Research
Classifier: License :: OSI Approved :: MIT License
Classifier: Programming Language :: Python :: 3
Classifier: Programming Language :: Python :: 3.10
Classifier: Programming Language :: Python :: 3.11
Classifier: Programming Language :: Python :: 3.12
Classifier: Topic :: Scientific/Engineering :: Medical Science Apps.
Requires-Python: >=3.10
License-File: LICENSE
Requires-Dist: polars>=1.0.0
Requires-Dist: pyarrow>=15.0.0
Requires-Dist: psutil>=5.9.0
Requires-Dist: tqdm>=4.67.1
Provides-Extra: dev
Requires-Dist: pytest>=7.0.0; extra == "dev"
Requires-Dist: pytest-cov>=4.0.0; extra == "dev"
Provides-Extra: config
Requires-Dist: python-dotenv>=1.0.0; extra == "config"
Dynamic: license-file
